setup.py
twitterads/__init__.py
twitterads/twitter_ads.py
twitterads.egg-info/PKG-INFO
twitterads.egg-info/SOURCES.txt
twitterads.egg-info/dependency_links.txt
twitterads.egg-info/requires.txt
twitterads.egg-info/top_level.txt
twitterads/helper/__init__.py
twitterads/helper/ton_api.py