Metadata-Version: 1.0
Name: twitterads
Version: 0.1.5
Summary: Wrapper to Twitter Ads Rest API.
Home-page: https://github.com/asamat/python_twitter_ads
Author: Arunim Samat
Author-email: arunimsamat@gmail.com
License: MIT License
Platform: UNKNOWN
